README.md
setup.py
wsnasa/__init__.py
wsnasa/config.py
wsnasa.egg-info/PKG-INFO
wsnasa.egg-info/SOURCES.txt
wsnasa.egg-info/dependency_links.txt
wsnasa.egg-info/requires.txt
wsnasa.egg-info/top_level.txt
wsnasa/entity/apod.py
wsnasa/entity/manifest.py
wsnasa/entity/storagedatabase.py
wsnasa/entity/storagefile.py
wsnasa/entity/storagememory.py
wsnasa/entity/abclass/abcapod.py
wsnasa/entity/abclass/abcrover.py
wsnasa/entity/abclass/abcstorage.py
wsnasa/services/__init__.py
wsnasa/services/apod/__init__.py
wsnasa/services/apod/apod.py
wsnasa/services/rovers/__init__.py
wsnasa/services/rovers/curiosity.py
wsnasa/services/rovers/opportunity.py
wsnasa/services/rovers/spirit.py
wsnasa/utils/makeuuid.py
wsnasa/utils/repo.py