Metadata-Version: 2.1
Name: wsnasa
Version: 0.0.2b0
Summary: Library for use nasa.api
Home-page: https://github.com/anikolaev82/nasaapi
Author: Artem Nikolaev
Author-email: anikolaev82@gmail.com
License: UNKNOWN
Platform: UNKNOWN
Classifier: Programming Language :: Python :: 3.9
